[
    {
        "noise_level": 0,
        "aps": [
            0.69324,
            0.50032,
            0.61746,
            0.40764,
            0.33958,
            0.76407,
            0.47709,
            0.78375,
            0.40462,
            0.67224,
            0.47244,
            0.66318,
            0.54989,
            0.56501,
            0.62558,
            0.30194,
            0.59586,
            0.51814,
            0.74749,
            0.49979
        ]        
    },
    {
        "noise_level": 1,
        "aps": [
            0.67197,
            0.44381,
            0.60863,
            0.38816,
            0.35307,
            0.75009,
            0.47337,
            0.73906,
            0.39321,
            0.63394,
            0.45222,
            0.65318,
            0.5373,
            0.51412,
            0.62383,
            0.28531,
            0.55174,
            0.50414,
            0.71118,
            0.43153
        ]        
    },
    {
        "noise_level": 2,
        "aps": [
            0.69432,
            0.45841,
            0.60727,
            0.385,
            0.33475,
            0.71893,
            0.48491,
            0.7441,
            0.37345,
            0.58554,
            0.42907,
            0.62802,
            0.54343,
            0.53388,
            0.61329,
            0.26345,
            0.54741,
            0.51625,
            0.70559,
            0.41398
        ]        
    },
    {
        "noise_level": 3,
        "aps": [
            0.65549,
            0.46239,
            0.58597,
            0.36736,
            0.32235,
            0.72421,
            0.47264,
            0.74196,
            0.37169,
            0.60745,
            0.44164,
            0.64714,
            0.53797,
            0.49787,
            0.60719,
            0.25155,
            0.55071,
            0.49088,
            0.69889,
            0.44057
        ]        
    },
    {
        "noise_level": 4,
        "aps": [
            0.66582,
            0.42066,
            0.55894,
            0.37834,
            0.34346,
            0.73855,
            0.47387,
            0.75108,
            0.37653,
            0.59902,
            0.42897,
            0.62241,
            0.51403,
            0.51553,
            0.60717,
            0.26296,
            0.5394,
            0.48514,
            0.69156,
            0.4315
        ]        
    },
    {
        "noise_level": 5,
        "aps": [
            0.68916,
            0.48884,
            0.60574,
            0.39195,
            0.36738,
            0.72116,
            0.48239,
            0.74145,
            0.41,
            0.61011,
            0.48554,
            0.64758,
            0.60081,
            0.57486,
            0.61668,
            0.26668,
            0.54573,
            0.5268,
            0.69991,
            0.45541
        ]        
    }
]